graph_nitta/__init__.py
graph_nitta/graph.py
graph_nitta/tools.py
graph_nitta/axes/config.py
graph_nitta/axes/resolver.py
graph_nitta/style/apply.py
graph_nitta/style/basic.mplstyle
graph_nitta-0.1.2.8.dist-info/METADATA
graph_nitta-0.1.2.8.dist-info/WHEEL
graph_nitta-0.1.2.8.dist-info/licenses/LICENSE
graph_nitta-0.1.2.8.dist-info/RECORD
